persiankivy/__init__.py
persiankivy-0.1.1.dist-info/METADATA
persiankivy-0.1.1.dist-info/WHEEL
persiankivy-0.1.1.dist-info/RECORD
